{
  "kitchen" : [    {
      "name" : "Age",
      "nid" : 30080,
      "food_color_background" : "F0E8C4",
      "food_color_text" : "131313",
      "category" : "chemical process, kitchen cards, process, chemistry, cooking, reactions, science, technique, cooking technique",
      "description" : "",
      "updated_date" : "Saturday, April 14, 2012 - 9:38",
      "datasource" : "@chachasikes: listing from memory & from scanning lists of food words."
    },
    {
      "name" : "Bake",
      "nid" : 30081,
      "food_color_background" : "F0E8C4",
      "food_color_text" : "131313",
      "category" : "chemical process, kitchen cards, process, chemistry, cooking, reactions, science, technique, cooking technique",
      "description" : "",
      "updated_date" : "Saturday, April 14, 2012 - 9:38",
      "datasource" : "@chachasikes: listing from memory & from scanning lists of food words."
    },
    {
      "name" : "Bread",
      "nid" : 30082,
      "food_color_background" : "F0E8C4",
      "food_color_text" : "131313",
      "category" : "chemical process, kitchen cards, process, chemistry, cooking, reactions, science, technique, cooking technique",
      "description" : "",
      "updated_date" : "Saturday, April 14, 2012 - 9:38",
      "datasource" : "@chachasikes: listing from memory & from scanning lists of food words."
    },
    {
      "name" : "Brine",
      "nid" : 30083,
      "food_color_background" : "F0E8C4",
      "food_color_text" : "131313",
      "category" : "chemical process, kitchen cards, process, chemistry, cooking, reactions, science, technique, cooking technique",
      "description" : "",
      "updated_date" : "Saturday, April 14, 2012 - 9:38",
      "datasource" : "@chachasikes: listing from memory & from scanning lists of food words."
    },
    {
      "name" : "Brown",
      "nid" : 30084,
      "food_color_background" : "F0E8C4",
      "food_color_text" : "131313",
      "category" : "chemical process, kitchen cards, process, chemistry, cooking, reactions, science, technique, cooking technique",
      "description" : "",
      "updated_date" : "Saturday, April 14, 2012 - 9:38",
      "datasource" : "@chachasikes: listing from memory & from scanning lists of food words."
    },
    {
      "name" : "Browning",
      "nid" : 30085,
      "food_color_background" : "F0E8C4",
      "food_color_text" : "131313",
      "category" : "chemical process, kitchen cards, process, chemistry, cooking, reactions, science, technique, cooking technique",
      "description" : "",
      "updated_date" : "Saturday, April 14, 2012 - 9:38",
      "datasource" : "@chachasikes: listing from memory & from scanning lists of food words."
    },
    {
      "name" : "Burn",
      "nid" : 30086,
      "food_color_background" : "F0E8C4",
      "food_color_text" : "131313",
      "category" : "chemical process, kitchen cards, process, chemistry, cooking, reactions, science, technique, cooking technique",
      "description" : "",
      "updated_date" : "Saturday, April 14, 2012 - 9:38",
      "datasource" : "@chachasikes: listing from memory & from scanning lists of food words."
    },
    {
      "name" : "Bury In Ground",
      "nid" : 30087,
      "food_color_background" : "F0E8C4",
      "food_color_text" : "131313",
      "category" : "chemical process, kitchen cards, process, chemistry, cooking, reactions, science, technique, cooking technique",
      "description" : "",
      "updated_date" : "Saturday, April 14, 2012 - 9:38",
      "datasource" : "@chachasikes: listing from memory & from scanning lists of food words."
    },
    {
      "name" : "Can",
      "nid" : 30088,
      "food_color_background" : "F0E8C4",
      "food_color_text" : "131313",
      "category" : "chemical process, kitchen cards, process, chemistry, cooking, reactions, science, technique, cooking technique",
      "description" : "",
      "updated_date" : "Saturday, April 14, 2012 - 9:38",
      "datasource" : "@chachasikes: listing from memory & from scanning lists of food words."
    },
    {
      "name" : "Candy",
      "nid" : 30089,
      "food_color_background" : "F0E8C4",
      "food_color_text" : "131313",
      "category" : "chemical process, kitchen cards, process, chemistry, cooking, reactions, science, technique, cooking technique",
      "description" : "",
      "updated_date" : "Saturday, April 14, 2012 - 9:38",
      "datasource" : "@chachasikes: listing from memory & from scanning lists of food words."
    },
    {
      "name" : "Caramelize",
      "nid" : 30093,
      "food_color_background" : "F0E8C4",
      "food_color_text" : "131313",
      "category" : "chemical process, kitchen cards, process, chemistry, cooking, reactions, science, technique, cooking technique",
      "description" : "",
      "updated_date" : "Saturday, April 14, 2012 - 9:38",
      "datasource" : "@chachasikes: listing from memory & from scanning lists of food words."
    },
    {
      "name" : "Carbonate",
      "nid" : 30094,
      "food_color_background" : "F0E8C4",
      "food_color_text" : "131313",
      "category" : "chemical process, kitchen cards, process, chemistry, cooking, reactions, science, technique, cooking technique",
      "description" : "",
      "updated_date" : "Saturday, April 14, 2012 - 9:38",
      "datasource" : "@chachasikes: listing from memory & from scanning lists of food words."
    },
    {
      "name" : "Ceviche",
      "nid" : 30095,
      "food_color_background" : "F0E8C4",
      "food_color_text" : "131313",
      "category" : "chemical process, kitchen cards, process, chemistry, cooking, reactions, science, technique, cooking technique",
      "description" : "",
      "updated_date" : "Saturday, April 14, 2012 - 9:38",
      "datasource" : "@chachasikes: listing from memory & from scanning lists of food words."
    },
    {
      "name" : "Char",
      "nid" : 30096,
      "food_color_background" : "F0E8C4",
      "food_color_text" : "131313",
      "category" : "chemical process, kitchen cards, process, chemistry, cooking, reactions, science, technique, cooking technique",
      "description" : "",
      "updated_date" : "Saturday, April 14, 2012 - 9:38",
      "datasource" : "@chachasikes: listing from memory & from scanning lists of food words."
    },
    {
      "name" : "Char-broil",
      "nid" : 30097,
      "food_color_background" : "F0E8C4",
      "food_color_text" : "131313",
      "category" : "chemical process, kitchen cards, process, chemistry, cooking, reactions, science, technique, cooking technique",
      "description" : "",
      "updated_date" : "Saturday, April 14, 2012 - 9:38",
      "datasource" : "@chachasikes: listing from memory & from scanning lists of food words."
    },
    {
      "name" : "Chemical Preservation",
      "nid" : 30098,
      "food_color_background" : "F0E8C4",
      "food_color_text" : "131313",
      "category" : "chemical process, kitchen cards, process, chemistry, cooking, reactions, science, technique, cooking technique",
      "description" : "",
      "updated_date" : "Saturday, April 14, 2012 - 9:38",
      "datasource" : "@chachasikes: listing from memory & from scanning lists of food words."
    },
    {
      "name" : "Clarify",
      "nid" : 30099,
      "food_color_background" : "F0E8C4",
      "food_color_text" : "131313",
      "category" : "chemical process, kitchen cards, process, chemistry, cooking, reactions, science, technique, cooking technique",
      "description" : "",
      "updated_date" : "Saturday, April 14, 2012 - 9:38",
      "datasource" : "@chachasikes: listing from memory & from scanning lists of food words."
    },
    {
      "name" : "Color",
      "nid" : 30100,
      "food_color_background" : "F0E8C4",
      "food_color_text" : "131313",
      "category" : "chemical process, kitchen cards, process, chemistry, cooking, reactions, science, technique, cooking technique",
      "description" : "",
      "updated_date" : "Saturday, April 14, 2012 - 9:38",
      "datasource" : "@chachasikes: listing from memory & from scanning lists of food words."
    },
    {
      "name" : "Cook With Wood",
      "nid" : 30101,
      "food_color_background" : "F0E8C4",
      "food_color_text" : "131313",
      "category" : "chemical process, kitchen cards, process, chemistry, cooking, reactions, science, technique, cooking technique",
      "description" : "",
      "updated_date" : "Saturday, April 14, 2012 - 9:38",
      "datasource" : "@chachasikes: listing from memory & from scanning lists of food words."
    },
    {
      "name" : "Curdle",
      "nid" : 30102,
      "food_color_background" : "F0E8C4",
      "food_color_text" : "131313",
      "category" : "chemical process, kitchen cards, process, chemistry, cooking, reactions, science, technique, cooking technique",
      "description" : "",
      "updated_date" : "Saturday, April 14, 2012 - 9:38",
      "datasource" : "@chachasikes: listing from memory & from scanning lists of food words."
    },
    {
      "name" : "Custard",
      "nid" : 30103,
      "food_color_background" : "F0E8C4",
      "food_color_text" : "131313",
      "category" : "chemical process, kitchen cards, process, chemistry, cooking, reactions, science, technique, cooking technique",
      "description" : "",
      "updated_date" : "Saturday, April 14, 2012 - 9:38",
      "datasource" : "@chachasikes: listing from memory & from scanning lists of food words."
    },
    {
      "name" : "Deep-fry",
      "nid" : 30104,
      "food_color_background" : "F0E8C4",
      "food_color_text" : "131313",
      "category" : "chemical process, kitchen cards, process, chemistry, cooking, reactions, science, technique, cooking technique",
      "description" : "",
      "updated_date" : "Saturday, April 14, 2012 - 9:38",
      "datasource" : "@chachasikes: listing from memory & from scanning lists of food words."
    },
    {
      "name" : "Denature",
      "nid" : 30105,
      "food_color_background" : "F0E8C4",
      "food_color_text" : "131313",
      "category" : "chemical process, kitchen cards, process, chemistry, cooking, reactions, science, technique, cooking technique",
      "description" : "",
      "updated_date" : "Saturday, April 14, 2012 - 9:38",
      "datasource" : "@chachasikes: listing from memory & from scanning lists of food words."
    },
    {
      "name" : "Dry",
      "nid" : 30106,
      "food_color_background" : "F0E8C4",
      "food_color_text" : "131313",
      "category" : "chemical process, kitchen cards, process, chemistry, cooking, reactions, science, technique, cooking technique",
      "description" : "",
      "updated_date" : "Saturday, April 14, 2012 - 9:38",
      "datasource" : "@chachasikes: listing from memory & from scanning lists of food words."
    },
    {
      "name" : "Emulsify",
      "nid" : 30107,
      "food_color_background" : "F0E8C4",
      "food_color_text" : "131313",
      "category" : "chemical process, kitchen cards, process, chemistry, cooking, reactions, science, technique, cooking technique",
      "description" : "",
      "updated_date" : "Saturday, April 14, 2012 - 9:38",
      "datasource" : "@chachasikes: listing from memory & from scanning lists of food words."
    },
    {
      "name" : "Enzymatic Browning",
      "nid" : 30108,
      "food_color_background" : "F0E8C4",
      "food_color_text" : "131313",
      "category" : "chemical process, kitchen cards, process, chemistry, cooking, reactions, science, technique, cooking technique",
      "description" : "",
      "updated_date" : "Saturday, April 14, 2012 - 9:38",
      "datasource" : "@chachasikes: listing from memory & from scanning lists of food words."
    },
    {
      "name" : "Ferment",
      "nid" : 30109,
      "food_color_background" : "F0E8C4",
      "food_color_text" : "131313",
      "category" : "chemical process, kitchen cards, process, chemistry, cooking, reactions, science, technique, cooking technique",
      "description" : "",
      "updated_date" : "Saturday, April 14, 2012 - 9:38",
      "datasource" : "@chachasikes: listing from memory & from scanning lists of food words."
    },
    {
      "name" : "Foam",
      "nid" : 30110,
      "food_color_background" : "F0E8C4",
      "food_color_text" : "131313",
      "category" : "chemical process, kitchen cards, process, chemistry, cooking, reactions, science, technique, cooking technique",
      "description" : "",
      "updated_date" : "Saturday, April 14, 2012 - 9:38",
      "datasource" : "@chachasikes: listing from memory & from scanning lists of food words."
    },
    {
      "name" : "Food Gel",
      "nid" : 30111,
      "food_color_background" : "F0E8C4",
      "food_color_text" : "131313",
      "category" : "chemical process, kitchen cards, process, chemistry, cooking, reactions, science, technique, cooking technique",
      "description" : "",
      "updated_date" : "Saturday, April 14, 2012 - 9:38",
      "datasource" : "@chachasikes: listing from memory & from scanning lists of food words."
    },
    {
      "name" : "Freeze Dry",
      "nid" : 30112,
      "food_color_background" : "F0E8C4",
      "food_color_text" : "131313",
      "category" : "chemical process, kitchen cards, process, chemistry, cooking, reactions, science, technique, cooking technique",
      "description" : "",
      "updated_date" : "Saturday, April 14, 2012 - 9:38",
      "datasource" : "@chachasikes: listing from memory & from scanning lists of food words."
    },
    {
      "name" : "Fresh",
      "nid" : 30113,
      "food_color_background" : "F0E8C4",
      "food_color_text" : "131313",
      "category" : "chemical process, kitchen cards, process, chemistry, cooking, reactions, science, technique, cooking technique",
      "description" : "",
      "updated_date" : "Saturday, April 14, 2012 - 9:38",
      "datasource" : "@chachasikes: listing from memory & from scanning lists of food words."
    },
    {
      "name" : "Fry",
      "nid" : 30114,
      "food_color_background" : "F0E8C4",
      "food_color_text" : "131313",
      "category" : "chemical process, kitchen cards, process, chemistry, cooking, reactions, science, technique, cooking technique",
      "description" : "",
      "updated_date" : "Saturday, April 14, 2012 - 9:38",
      "datasource" : "@chachasikes: listing from memory & from scanning lists of food words."
    },
    {
      "name" : "Gelatin",
      "nid" : 30115,
      "food_color_background" : "F0E8C4",
      "food_color_text" : "131313",
      "category" : "chemical process, kitchen cards, process, chemistry, cooking, reactions, science, technique, cooking technique",
      "description" : "",
      "updated_date" : "Saturday, April 14, 2012 - 9:38",
      "datasource" : "@chachasikes: listing from memory & from scanning lists of food words."
    },
    {
      "name" : "Gelatinate",
      "nid" : 30173,
      "food_color_background" : "F0E8C4",
      "food_color_text" : "131313",
      "category" : "chemical process, kitchen cards, process, chemistry, cooking, reactions, science, technique, cooking technique",
      "description" : "",
      "updated_date" : "Saturday, April 14, 2012 - 9:38",
      "datasource" : "@chachasikes: listing from memory & from scanning lists of food words."
    },
    {
      "name" : "Grill",
      "nid" : 30116,
      "food_color_background" : "F0E8C4",
      "food_color_text" : "131313",
      "category" : "chemical process, kitchen cards, process, chemistry, cooking, reactions, science, technique, cooking technique",
      "description" : "",
      "updated_date" : "Saturday, April 14, 2012 - 9:38",
      "datasource" : "@chachasikes: listing from memory & from scanning lists of food words."
    },
    {
      "name" : "Hard Ball Candy",
      "nid" : 30090,
      "food_color_background" : "F0E8C4",
      "food_color_text" : "131313",
      "category" : "chemical process, kitchen cards, process, chemistry, cooking, reactions, science, technique, cooking technique",
      "description" : "",
      "updated_date" : "Saturday, April 14, 2012 - 9:38",
      "datasource" : "@chachasikes: listing from memory & from scanning lists of food words."
    },
    {
      "name" : "Hardboil",
      "nid" : 30118,
      "food_color_background" : "F0E8C4",
      "food_color_text" : "131313",
      "category" : "chemical process, kitchen cards, process, chemistry, cooking, reactions, science, technique, cooking technique",
      "description" : "",
      "updated_date" : "Saturday, April 14, 2012 - 9:38",
      "datasource" : "@chachasikes: listing from memory & from scanning lists of food words."
    },
    {
      "name" : "Hard Crack",
      "nid" : 30117,
      "food_color_background" : "F0E8C4",
      "food_color_text" : "131313",
      "category" : "chemical process, kitchen cards, process, chemistry, cooking, reactions, science, technique, cooking technique",
      "description" : "",
      "updated_date" : "Saturday, April 14, 2012 - 9:38",
      "datasource" : "@chachasikes: listing from memory & from scanning lists of food words."
    },
    {
      "name" : "High Pressure Cook",
      "nid" : 30119,
      "food_color_background" : "F0E8C4",
      "food_color_text" : "131313",
      "category" : "chemical process, kitchen cards, process, chemistry, cooking, reactions, science, technique, cooking technique",
      "description" : "",
      "updated_date" : "Saturday, April 14, 2012 - 9:38",
      "datasource" : "@chachasikes: listing from memory & from scanning lists of food words."
    },
    {
      "name" : "Honey",
      "nid" : 30120,
      "food_color_background" : "F0E8C4",
      "food_color_text" : "131313",
      "category" : "chemical process, kitchen cards, process, chemistry, cooking, reactions, science, technique, cooking technique",
      "description" : "",
      "updated_date" : "Saturday, April 14, 2012 - 9:38",
      "datasource" : "@chachasikes: listing from memory & from scanning lists of food words."
    },
    {
      "name" : "Honey-glaze",
      "nid" : 30121,
      "food_color_background" : "F0E8C4",
      "food_color_text" : "131313",
      "category" : "chemical process, kitchen cards, process, chemistry, cooking, reactions, science, technique, cooking technique",
      "description" : "",
      "updated_date" : "Saturday, April 14, 2012 - 9:38",
      "datasource" : "@chachasikes: listing from memory & from scanning lists of food words."
    },
    {
      "name" : "Hydrate",
      "nid" : 30122,
      "food_color_background" : "F0E8C4",
      "food_color_text" : "131313",
      "category" : "chemical process, kitchen cards, process, chemistry, cooking, reactions, science, technique, cooking technique",
      "description" : "",
      "updated_date" : "Saturday, April 14, 2012 - 9:38",
      "datasource" : "@chachasikes: listing from memory & from scanning lists of food words."
    },
    {
      "name" : "Infuse",
      "nid" : 30123,
      "food_color_background" : "F0E8C4",
      "food_color_text" : "131313",
      "category" : "chemical process, kitchen cards, process, chemistry, cooking, reactions, science, technique, cooking technique",
      "description" : "",
      "updated_date" : "Saturday, April 14, 2012 - 9:38",
      "datasource" : "@chachasikes: listing from memory & from scanning lists of food words."
    },
    {
      "name" : "Inoculate",
      "nid" : 30092,
      "food_color_background" : "F0E8C4",
      "food_color_text" : "131313",
      "category" : "chemical process, kitchen cards, process, chemistry, cooking, reactions, science, technique, cooking technique",
      "description" : "",
      "updated_date" : "Saturday, April 14, 2012 - 9:38",
      "datasource" : "@chachasikes: listing from memory & from scanning lists of food words."
    },
    {
      "name" : "Jam",
      "nid" : 30124,
      "food_color_background" : "F0E8C4",
      "food_color_text" : "131313",
      "category" : "chemical process, kitchen cards, process, chemistry, cooking, reactions, science, technique, cooking technique",
      "description" : "",
      "updated_date" : "Saturday, April 14, 2012 - 9:38",
      "datasource" : "@chachasikes: listing from memory & from scanning lists of food words."
    },
    {
      "name" : "Jelly",
      "nid" : 30125,
      "food_color_background" : "F0E8C4",
      "food_color_text" : "131313",
      "category" : "chemical process, kitchen cards, process, chemistry, cooking, reactions, science, technique, cooking technique",
      "description" : "",
      "updated_date" : "Saturday, April 14, 2012 - 9:38",
      "datasource" : "@chachasikes: listing from memory & from scanning lists of food words."
    },
    {
      "name" : "Jug Preservation",
      "nid" : 30126,
      "food_color_background" : "F0E8C4",
      "food_color_text" : "131313",
      "category" : "chemical process, kitchen cards, process, chemistry, cooking, reactions, science, technique, cooking technique",
      "description" : "",
      "updated_date" : "Saturday, April 14, 2012 - 9:38",
      "datasource" : "@chachasikes: listing from memory & from scanning lists of food words."
    },
    {
      "name" : "Leaven",
      "nid" : 30127,
      "food_color_background" : "F0E8C4",
      "food_color_text" : "131313",
      "category" : "chemical process, kitchen cards, process, chemistry, cooking, reactions, science, technique, cooking technique",
      "description" : "",
      "updated_date" : "Saturday, April 14, 2012 - 9:38",
      "datasource" : "@chachasikes: listing from memory & from scanning lists of food words."
    },
    {
      "name" : "Lye",
      "nid" : 30128,
      "food_color_background" : "F0E8C4",
      "food_color_text" : "131313",
      "category" : "chemical process, kitchen cards, process, chemistry, cooking, reactions, science, technique, cooking technique",
      "description" : "",
      "updated_date" : "Saturday, April 14, 2012 - 9:38",
      "datasource" : "@chachasikes: listing from memory & from scanning lists of food words."
    },
    {
      "name" : "Maillard Reaction",
      "nid" : 30129,
      "food_color_background" : "F0E8C4",
      "food_color_text" : "131313",
      "category" : "chemical process, kitchen cards, process, chemistry, cooking, reactions, science, technique, cooking technique",
      "description" : "",
      "updated_date" : "Saturday, April 14, 2012 - 9:38",
      "datasource" : "@chachasikes: listing from memory & from scanning lists of food words."
    },
    {
      "name" : "Marinate",
      "nid" : 30130,
      "food_color_background" : "F0E8C4",
      "food_color_text" : "131313",
      "category" : "chemical process, kitchen cards, process, chemistry, cooking, reactions, science, technique, cooking technique",
      "description" : "",
      "updated_date" : "Saturday, April 14, 2012 - 9:38",
      "datasource" : "@chachasikes: listing from memory & from scanning lists of food words."
    },
    {
      "name" : "Microencapsulation",
      "nid" : 30131,
      "food_color_background" : "F0E8C4",
      "food_color_text" : "131313",
      "category" : "chemical process, kitchen cards, process, chemistry, cooking, reactions, science, technique, cooking technique",
      "description" : "",
      "updated_date" : "Saturday, April 14, 2012 - 9:38",
      "datasource" : "@chachasikes: listing from memory & from scanning lists of food words."
    },
    {
      "name" : "Nitrogen Freeze",
      "nid" : 30132,
      "food_color_background" : "F0E8C4",
      "food_color_text" : "131313",
      "category" : "chemical process, kitchen cards, process, chemistry, cooking, reactions, science, technique, cooking technique",
      "description" : "",
      "updated_date" : "Saturday, April 14, 2012 - 9:38",
      "datasource" : "@chachasikes: listing from memory & from scanning lists of food words."
    },
    {
      "name" : "Pan-fry",
      "nid" : 30133,
      "food_color_background" : "F0E8C4",
      "food_color_text" : "131313",
      "category" : "chemical process, kitchen cards, process, chemistry, cooking, reactions, science, technique, cooking technique",
      "description" : "",
      "updated_date" : "Saturday, April 14, 2012 - 9:38",
      "datasource" : "@chachasikes: listing from memory & from scanning lists of food words."
    },
    {
      "name" : "Parboil",
      "nid" : 30134,
      "food_color_background" : "F0E8C4",
      "food_color_text" : "131313",
      "category" : "chemical process, kitchen cards, process, chemistry, cooking, reactions, science, technique, cooking technique",
      "description" : "",
      "updated_date" : "Saturday, April 14, 2012 - 9:38",
      "datasource" : "@chachasikes: listing from memory & from scanning lists of food words."
    },
    {
      "name" : "Parch",
      "nid" : 30135,
      "food_color_background" : "F0E8C4",
      "food_color_text" : "131313",
      "category" : "chemical process, kitchen cards, process, chemistry, cooking, reactions, science, technique, cooking technique",
      "description" : "",
      "updated_date" : "Saturday, April 14, 2012 - 9:38",
      "datasource" : "@chachasikes: listing from memory & from scanning lists of food words."
    },
    {
      "name" : "Perfume",
      "nid" : 30136,
      "food_color_background" : "F0E8C4",
      "food_color_text" : "131313",
      "category" : "chemical process, kitchen cards, process, chemistry, cooking, reactions, science, technique, cooking technique",
      "description" : "",
      "updated_date" : "Saturday, April 14, 2012 - 9:38",
      "datasource" : "@chachasikes: listing from memory & from scanning lists of food words."
    },
    {
      "name" : "Pickle",
      "nid" : 30137,
      "food_color_background" : "F0E8C4",
      "food_color_text" : "131313",
      "category" : "chemical process, kitchen cards, process, chemistry, cooking, reactions, science, technique, cooking technique",
      "description" : "",
      "updated_date" : "Saturday, April 14, 2012 - 9:38",
      "datasource" : "@chachasikes: listing from memory & from scanning lists of food words."
    },
    {
      "name" : "Pot Preservation",
      "nid" : 30138,
      "food_color_background" : "F0E8C4",
      "food_color_text" : "131313",
      "category" : "chemical process, kitchen cards, process, chemistry, cooking, reactions, science, technique, cooking technique",
      "description" : "",
      "updated_date" : "Saturday, April 14, 2012 - 9:38",
      "datasource" : "@chachasikes: listing from memory & from scanning lists of food words."
    },
    {
      "name" : "Preserve",
      "nid" : 30139,
      "food_color_background" : "F0E8C4",
      "food_color_text" : "131313",
      "category" : "chemical process, kitchen cards, process, chemistry, cooking, reactions, science, technique, cooking technique",
      "description" : "",
      "updated_date" : "Saturday, April 14, 2012 - 9:38",
      "datasource" : "@chachasikes: listing from memory & from scanning lists of food words."
    },
    {
      "name" : "Raw",
      "nid" : 30140,
      "food_color_background" : "F0E8C4",
      "food_color_text" : "131313",
      "category" : "chemical process, kitchen cards, process, chemistry, cooking, reactions, science, technique, cooking technique",
      "description" : "",
      "updated_date" : "Saturday, April 14, 2012 - 9:38",
      "datasource" : "@chachasikes: listing from memory & from scanning lists of food words."
    },
    {
      "name" : "Reduce",
      "nid" : 30141,
      "food_color_background" : "F0E8C4",
      "food_color_text" : "131313",
      "category" : "chemical process, kitchen cards, process, chemistry, cooking, reactions, science, technique, cooking technique",
      "description" : "",
      "updated_date" : "Saturday, April 14, 2012 - 9:38",
      "datasource" : "@chachasikes: listing from memory & from scanning lists of food words."
    },
    {
      "name" : "Relish",
      "nid" : 30142,
      "food_color_background" : "F0E8C4",
      "food_color_text" : "131313",
      "category" : "chemical process, kitchen cards, process, chemistry, cooking, reactions, science, technique, cooking technique",
      "description" : "",
      "updated_date" : "Saturday, April 14, 2012 - 9:38",
      "datasource" : "@chachasikes: listing from memory & from scanning lists of food words."
    },
    {
      "name" : "Ripen",
      "nid" : 30143,
      "food_color_background" : "F0E8C4",
      "food_color_text" : "131313",
      "category" : "chemical process, kitchen cards, process, chemistry, cooking, reactions, science, technique, cooking technique",
      "description" : "",
      "updated_date" : "Saturday, April 14, 2012 - 9:38",
      "datasource" : "@chachasikes: listing from memory & from scanning lists of food words."
    },
    {
      "name" : "Roast",
      "nid" : 30144,
      "food_color_background" : "F0E8C4",
      "food_color_text" : "131313",
      "category" : "chemical process, kitchen cards, process, chemistry, cooking, reactions, science, technique, cooking technique",
      "description" : "",
      "updated_date" : "Saturday, April 14, 2012 - 9:38",
      "datasource" : "@chachasikes: listing from memory & from scanning lists of food words."
    },
    {
      "name" : "Roux",
      "nid" : 30145,
      "food_color_background" : "F0E8C4",
      "food_color_text" : "131313",
      "category" : "chemical process, kitchen cards, process, chemistry, cooking, reactions, science, technique, cooking technique",
      "description" : "",
      "updated_date" : "Saturday, April 14, 2012 - 9:38",
      "datasource" : "@chachasikes: listing from memory & from scanning lists of food words."
    },
    {
      "name" : "Saline",
      "nid" : 30146,
      "food_color_background" : "F0E8C4",
      "food_color_text" : "131313",
      "category" : "chemical process, kitchen cards, process, chemistry, cooking, reactions, science, technique, cooking technique",
      "description" : "",
      "updated_date" : "Saturday, April 14, 2012 - 9:38",
      "datasource" : "@chachasikes: listing from memory & from scanning lists of food words."
    },
    {
      "name" : "Salt Rub",
      "nid" : 30147,
      "food_color_background" : "F0E8C4",
      "food_color_text" : "131313",
      "category" : "chemical process, kitchen cards, process, chemistry, cooking, reactions, science, technique, cooking technique",
      "description" : "",
      "updated_date" : "Saturday, April 14, 2012 - 9:38",
      "datasource" : "@chachasikes: listing from memory & from scanning lists of food words."
    },
    {
      "name" : "Salty",
      "nid" : 30148,
      "food_color_background" : "F0E8C4",
      "food_color_text" : "131313",
      "category" : "chemical process, kitchen cards, process, chemistry, cooking, reactions, science, technique, cooking technique",
      "description" : "",
      "updated_date" : "Saturday, April 14, 2012 - 9:38",
      "datasource" : "@chachasikes: listing from memory & from scanning lists of food words."
    },
    {
      "name" : "Sauté",
      "nid" : 30149,
      "food_color_background" : "F0E8C4",
      "food_color_text" : "131313",
      "category" : "chemical process, kitchen cards, process, chemistry, cooking, reactions, science, technique, cooking technique",
      "description" : "",
      "updated_date" : "Saturday, April 14, 2012 - 9:38",
      "datasource" : "@chachasikes: listing from memory & from scanning lists of food words."
    },
    {
      "name" : "Scald",
      "nid" : 30150,
      "food_color_background" : "F0E8C4",
      "food_color_text" : "131313",
      "category" : "chemical process, kitchen cards, process, chemistry, cooking, reactions, science, technique, cooking technique",
      "description" : "",
      "updated_date" : "Saturday, April 14, 2012 - 9:38",
      "datasource" : "@chachasikes: listing from memory & from scanning lists of food words."
    },
    {
      "name" : "Scent",
      "nid" : 30151,
      "food_color_background" : "F0E8C4",
      "food_color_text" : "131313",
      "category" : "chemical process, kitchen cards, process, chemistry, cooking, reactions, science, technique, cooking technique",
      "description" : "",
      "updated_date" : "Saturday, April 14, 2012 - 9:38",
      "datasource" : "@chachasikes: listing from memory & from scanning lists of food words."
    },
    {
      "name" : "Scorch",
      "nid" : 30152,
      "food_color_background" : "F0E8C4",
      "food_color_text" : "131313",
      "category" : "chemical process, kitchen cards, process, chemistry, cooking, reactions, science, technique, cooking technique",
      "description" : "",
      "updated_date" : "Saturday, April 14, 2012 - 9:38",
      "datasource" : "@chachasikes: listing from memory & from scanning lists of food words."
    },
    {
      "name" : "Sear",
      "nid" : 30153,
      "food_color_background" : "F0E8C4",
      "food_color_text" : "131313",
      "category" : "chemical process, kitchen cards, process, chemistry, cooking, reactions, science, technique, cooking technique",
      "description" : "",
      "updated_date" : "Saturday, April 14, 2012 - 9:38",
      "datasource" : "@chachasikes: listing from memory & from scanning lists of food words."
    },
    {
      "name" : "Simmer",
      "nid" : 30154,
      "food_color_background" : "F0E8C4",
      "food_color_text" : "131313",
      "category" : "chemical process, kitchen cards, process, chemistry, cooking, reactions, science, technique, cooking technique",
      "description" : "",
      "updated_date" : "Saturday, April 14, 2012 - 9:38",
      "datasource" : "@chachasikes: listing from memory & from scanning lists of food words."
    },
    {
      "name" : "Sizzle",
      "nid" : 30155,
      "food_color_background" : "F0E8C4",
      "food_color_text" : "131313",
      "category" : "chemical process, kitchen cards, process, chemistry, cooking, reactions, science, technique, cooking technique",
      "description" : "",
      "updated_date" : "Saturday, April 14, 2012 - 9:38",
      "datasource" : "@chachasikes: listing from memory & from scanning lists of food words."
    },
    {
      "name" : "Slow-cook",
      "nid" : 30156,
      "food_color_background" : "F0E8C4",
      "food_color_text" : "131313",
      "category" : "chemical process, kitchen cards, process, chemistry, cooking, reactions, science, technique, cooking technique",
      "description" : "",
      "updated_date" : "Saturday, April 14, 2012 - 9:38",
      "datasource" : "@chachasikes: listing from memory & from scanning lists of food words."
    },
    {
      "name" : "Smoke",
      "nid" : 30157,
      "food_color_background" : "F0E8C4",
      "food_color_text" : "131313",
      "category" : "chemical process, kitchen cards, process, chemistry, cooking, reactions, science, technique, cooking technique",
      "description" : "",
      "updated_date" : "Saturday, April 14, 2012 - 9:38",
      "datasource" : "@chachasikes: listing from memory & from scanning lists of food words."
    },
    {
      "name" : "Soft Ball Candy",
      "nid" : 30091,
      "food_color_background" : "F0E8C4",
      "food_color_text" : "131313",
      "category" : "chemical process, kitchen cards, process, chemistry, cooking, reactions, science, technique, cooking technique",
      "description" : "",
      "updated_date" : "Saturday, April 14, 2012 - 9:38",
      "datasource" : "@chachasikes: listing from memory & from scanning lists of food words."
    },
    {
      "name" : "Soft-boil",
      "nid" : 30159,
      "food_color_background" : "F0E8C4",
      "food_color_text" : "131313",
      "category" : "chemical process, kitchen cards, process, chemistry, cooking, reactions, science, technique, cooking technique",
      "description" : "",
      "updated_date" : "Saturday, April 14, 2012 - 9:38",
      "datasource" : "@chachasikes: listing from memory & from scanning lists of food words."
    },
    {
      "name" : "Soft Crack",
      "nid" : 30158,
      "food_color_background" : "F0E8C4",
      "food_color_text" : "131313",
      "category" : "chemical process, kitchen cards, process, chemistry, cooking, reactions, science, technique, cooking technique",
      "description" : "",
      "updated_date" : "Saturday, April 14, 2012 - 9:38",
      "datasource" : "@chachasikes: listing from memory & from scanning lists of food words."
    },
    {
      "name" : "Solidify",
      "nid" : 30172,
      "food_color_background" : "F0E8C4",
      "food_color_text" : "131313",
      "category" : "chemical process, kitchen cards, process, chemistry, cooking, reactions, science, technique, cooking technique",
      "description" : "",
      "updated_date" : "Saturday, April 14, 2012 - 9:38",
      "datasource" : "@chachasikes: listing from memory & from scanning lists of food words."
    },
    {
      "name" : "Souffle",
      "nid" : 30160,
      "food_color_background" : "F0E8C4",
      "food_color_text" : "131313",
      "category" : "chemical process, kitchen cards, process, chemistry, cooking, reactions, science, technique, cooking technique",
      "description" : "",
      "updated_date" : "Saturday, April 14, 2012 - 9:38",
      "datasource" : "@chachasikes: listing from memory & from scanning lists of food words."
    },
    {
      "name" : "Spherificate",
      "nid" : 30161,
      "food_color_background" : "F0E8C4",
      "food_color_text" : "131313",
      "category" : "chemical process, kitchen cards, process, chemistry, cooking, reactions, science, technique, cooking technique",
      "description" : "",
      "updated_date" : "Saturday, April 14, 2012 - 9:38",
      "datasource" : "@chachasikes: listing from memory & from scanning lists of food words."
    },
    {
      "name" : "Spice",
      "nid" : 30162,
      "food_color_background" : "F0E8C4",
      "food_color_text" : "131313",
      "category" : "chemical process, kitchen cards, process, chemistry, cooking, reactions, science, technique, cooking technique",
      "description" : "",
      "updated_date" : "Saturday, April 14, 2012 - 9:38",
      "datasource" : "@chachasikes: listing from memory & from scanning lists of food words."
    },
    {
      "name" : "Starch Gelatinization",
      "nid" : 30163,
      "food_color_background" : "F0E8C4",
      "food_color_text" : "131313",
      "category" : "chemical process, kitchen cards, process, chemistry, cooking, reactions, science, technique, cooking technique",
      "description" : "",
      "updated_date" : "Saturday, April 14, 2012 - 9:38",
      "datasource" : "@chachasikes: listing from memory & from scanning lists of food words."
    },
    {
      "name" : "Steam",
      "nid" : 30164,
      "food_color_background" : "F0E8C4",
      "food_color_text" : "131313",
      "category" : "chemical process, kitchen cards, process, chemistry, cooking, reactions, science, technique, cooking technique",
      "description" : "",
      "updated_date" : "Saturday, April 14, 2012 - 9:38",
      "datasource" : "@chachasikes: listing from memory & from scanning lists of food words."
    },
    {
      "name" : "Stew",
      "nid" : 30165,
      "food_color_background" : "F0E8C4",
      "food_color_text" : "131313",
      "category" : "chemical process, kitchen cards, process, chemistry, cooking, reactions, science, technique, cooking technique",
      "description" : "",
      "updated_date" : "Saturday, April 14, 2012 - 9:38",
      "datasource" : "@chachasikes: listing from memory & from scanning lists of food words."
    },
    {
      "name" : "Sugarcoat",
      "nid" : 30166,
      "food_color_background" : "F0E8C4",
      "food_color_text" : "131313",
      "category" : "chemical process, kitchen cards, process, chemistry, cooking, reactions, science, technique, cooking technique",
      "description" : "",
      "updated_date" : "Saturday, April 14, 2012 - 9:38",
      "datasource" : "@chachasikes: listing from memory & from scanning lists of food words."
    },
    {
      "name" : "Tender",
      "nid" : 30167,
      "food_color_background" : "F0E8C4",
      "food_color_text" : "131313",
      "category" : "chemical process, kitchen cards, process, chemistry, cooking, reactions, science, technique, cooking technique",
      "description" : "",
      "updated_date" : "Saturday, April 14, 2012 - 9:38",
      "datasource" : "@chachasikes: listing from memory & from scanning lists of food words."
    },
    {
      "name" : "Tepid",
      "nid" : 30168,
      "food_color_background" : "F0E8C4",
      "food_color_text" : "131313",
      "category" : "chemical process, kitchen cards, process, chemistry, cooking, reactions, science, technique, cooking technique",
      "description" : "",
      "updated_date" : "Saturday, April 14, 2012 - 9:38",
      "datasource" : "@chachasikes: listing from memory & from scanning lists of food words."
    },
    {
      "name" : "Toast",
      "nid" : 30169,
      "food_color_background" : "F0E8C4",
      "food_color_text" : "131313",
      "category" : "chemical process, kitchen cards, process, chemistry, cooking, reactions, science, technique, cooking technique",
      "description" : "",
      "updated_date" : "Saturday, April 14, 2012 - 9:38",
      "datasource" : "@chachasikes: listing from memory & from scanning lists of food words."
    },
    {
      "name" : "Whip",
      "nid" : 30171,
      "food_color_background" : "F0E8C4",
      "food_color_text" : "131313",
      "category" : "chemical process, kitchen cards, process, chemistry, cooking, reactions, science, technique, cooking technique",
      "description" : "",
      "updated_date" : "Saturday, April 14, 2012 - 9:38",
      "datasource" : "@chachasikes: listing from memory & from scanning lists of food words."
    },

    {
      "name" : "Baste",
      "nid" : 30201,
      "category" : "physical, kitchen cards, physical process, cooking, technique, cooking technique",
      "updated_date" : "Saturday, April 14, 2012 - 9:48",
      "datasource" : "@chachasikes: listing from memory & from scanning lists of food words.",
      "food_color_background" : "C0BFC4",
      "food_color_text" : "131313"
    },
    {
      "name" : "Blanch",
      "nid" : 30202,
      "category" : "physical, kitchen cards, physical process, cooking, technique, cooking technique",
      "updated_date" : "Saturday, April 14, 2012 - 9:48",
      "datasource" : "@chachasikes: listing from memory & from scanning lists of food words.",
      "food_color_background" : "C0BFC4",
      "food_color_text" : "131313"
    },
    {
      "name" : "Blend",
      "nid" : 30203,
      "category" : "physical, kitchen cards, physical process, cooking, technique, cooking technique",
      "updated_date" : "Saturday, April 14, 2012 - 9:48",
      "datasource" : "@chachasikes: listing from memory & from scanning lists of food words.",
      "food_color_background" : "C0BFC4",
      "food_color_text" : "131313"
    },
    {
      "name" : "Boil",
      "nid" : 30204,
      "category" : "physical, kitchen cards, physical process, cooking, technique, cooking technique",
      "updated_date" : "Saturday, April 14, 2012 - 9:48",
      "datasource" : "@chachasikes: listing from memory & from scanning lists of food words.",
      "food_color_background" : "C0BFC4",
      "food_color_text" : "131313"
    },
    {
      "name" : "Broil",
      "nid" : 30205,
      "category" : "physical, kitchen cards, physical process, cooking, technique, cooking technique",
      "updated_date" : "Saturday, April 14, 2012 - 9:48",
      "datasource" : "@chachasikes: listing from memory & from scanning lists of food words.",
      "food_color_background" : "C0BFC4",
      "food_color_text" : "131313"
    },
    {
      "name" : "Can",
      "nid" : 30206,
      "category" : "physical, kitchen cards, physical process, cooking, technique, cooking technique",
      "updated_date" : "Saturday, April 14, 2012 - 9:48",
      "datasource" : "@chachasikes: listing from memory & from scanning lists of food words.",
      "food_color_background" : "C0BFC4",
      "food_color_text" : "131313"
    },
    {
      "name" : "Chill",
      "nid" : 30207,
      "category" : "physical, kitchen cards, physical process, cooking, technique, cooking technique",
      "updated_date" : "Saturday, April 14, 2012 - 9:48",
      "datasource" : "@chachasikes: listing from memory & from scanning lists of food words.",
      "food_color_background" : "C0BFC4",
      "food_color_text" : "131313"
    },
    {
      "name" : "Cool",
      "nid" : 30208,
      "category" : "physical, kitchen cards, physical process, cooking, technique, cooking technique",
      "updated_date" : "Saturday, April 14, 2012 - 9:48",
      "datasource" : "@chachasikes: listing from memory & from scanning lists of food words.",
      "food_color_background" : "C0BFC4",
      "food_color_text" : "131313"
    },
    {
      "name" : "Craft",
      "nid" : 30209,
      "category" : "physical, kitchen cards, physical process, cooking, technique, cooking technique",
      "updated_date" : "Saturday, April 14, 2012 - 9:48",
      "datasource" : "@chachasikes: listing from memory & from scanning lists of food words.",
      "food_color_background" : "C0BFC4",
      "food_color_text" : "131313"
    },
    {
      "name" : "Cream",
      "nid" : 30210,
      "category" : "physical, kitchen cards, physical process, cooking, technique, cooking technique",
      "updated_date" : "Saturday, April 14, 2012 - 9:48",
      "datasource" : "@chachasikes: listing from memory & from scanning lists of food words.",
      "food_color_background" : "C0BFC4",
      "food_color_text" : "131313"
    },
    {
      "name" : "Crush",
      "nid" : 30211,
      "category" : "physical, kitchen cards, physical process, cooking, technique, cooking technique",
      "updated_date" : "Saturday, April 14, 2012 - 9:48",
      "datasource" : "@chachasikes: listing from memory & from scanning lists of food words.",
      "food_color_background" : "C0BFC4",
      "food_color_text" : "131313"
    },
    {
      "name" : "Cut",
      "nid" : 30212,
      "category" : "physical, kitchen cards, physical process, cooking, technique, cooking technique",
      "updated_date" : "Saturday, April 14, 2012 - 9:48",
      "datasource" : "@chachasikes: listing from memory & from scanning lists of food words.",
      "food_color_background" : "C0BFC4",
      "food_color_text" : "131313"
    },
    {
      "name" : "Dehydrate",
      "nid" : 30213,
      "category" : "physical, kitchen cards, physical process, cooking, technique, cooking technique",
      "updated_date" : "Saturday, April 14, 2012 - 9:48",
      "datasource" : "@chachasikes: listing from memory & from scanning lists of food words.",
      "food_color_background" : "C0BFC4",
      "food_color_text" : "131313"
    },
    {
      "name" : "Dilute",
      "nid" : 30214,
      "category" : "physical, kitchen cards, physical process, cooking, technique, cooking technique",
      "updated_date" : "Saturday, April 14, 2012 - 9:48",
      "datasource" : "@chachasikes: listing from memory & from scanning lists of food words.",
      "food_color_background" : "C0BFC4",
      "food_color_text" : "131313"
    },
    {
      "name" : "Distill",
      "nid" : 30215,
      "category" : "physical, kitchen cards, physical process, cooking, technique, cooking technique",
      "updated_date" : "Saturday, April 14, 2012 - 9:48",
      "datasource" : "@chachasikes: listing from memory & from scanning lists of food words.",
      "food_color_background" : "C0BFC4",
      "food_color_text" : "131313"
    },
    {
      "name" : "Dress",
      "nid" : 30216,
      "category" : "physical, kitchen cards, physical process, cooking, technique, cooking technique",
      "updated_date" : "Saturday, April 14, 2012 - 9:48",
      "datasource" : "@chachasikes: listing from memory & from scanning lists of food words.",
      "food_color_background" : "C0BFC4",
      "food_color_text" : "131313"
    },
    {
      "name" : "Drip",
      "nid" : 30217,
      "category" : "physical, kitchen cards, physical process, cooking, technique, cooking technique",
      "updated_date" : "Saturday, April 14, 2012 - 9:48",
      "datasource" : "@chachasikes: listing from memory & from scanning lists of food words.",
      "food_color_background" : "C0BFC4",
      "food_color_text" : "131313"
    },
    {
      "name" : "Drizzle",
      "nid" : 30218,
      "category" : "physical, kitchen cards, physical process, cooking, technique, cooking technique",
      "updated_date" : "Saturday, April 14, 2012 - 9:48",
      "datasource" : "@chachasikes: listing from memory & from scanning lists of food words.",
      "food_color_background" : "C0BFC4",
      "food_color_text" : "131313"
    },
    {
      "name" : "Dry",
      "nid" : 30219,
      "category" : "physical, kitchen cards, physical process, cooking, technique, cooking technique",
      "updated_date" : "Saturday, April 14, 2012 - 9:48",
      "datasource" : "@chachasikes: listing from memory & from scanning lists of food words.",
      "food_color_background" : "C0BFC4",
      "food_color_text" : "131313"
    },
    {
      "name" : "Freeze",
      "nid" : 30220,
      "category" : "physical, kitchen cards, physical process, cooking, technique, cooking technique",
      "updated_date" : "Saturday, April 14, 2012 - 9:48",
      "datasource" : "@chachasikes: listing from memory & from scanning lists of food words.",
      "food_color_background" : "C0BFC4",
      "food_color_text" : "131313"
    },
    {
      "name" : "Frosty",
      "nid" : 30221,
      "category" : "physical, kitchen cards, physical process, cooking, technique, cooking technique",
      "updated_date" : "Saturday, April 14, 2012 - 9:48",
      "datasource" : "@chachasikes: listing from memory & from scanning lists of food words.",
      "food_color_background" : "C0BFC4",
      "food_color_text" : "131313"
    },
    {
      "name" : "Glaze",
      "nid" : 30222,
      "category" : "physical, kitchen cards, physical process, cooking, technique, cooking technique",
      "updated_date" : "Saturday, April 14, 2012 - 9:48",
      "datasource" : "@chachasikes: listing from memory & from scanning lists of food words.",
      "food_color_background" : "C0BFC4",
      "food_color_text" : "131313"
    },
    {
      "name" : "Griddle",
      "nid" : 30223,
      "category" : "physical, kitchen cards, physical process, cooking, technique, cooking technique",
      "updated_date" : "Saturday, April 14, 2012 - 9:48",
      "datasource" : "@chachasikes: listing from memory & from scanning lists of food words.",
      "food_color_background" : "C0BFC4",
      "food_color_text" : "131313"
    },
    {
      "name" : "Grind",
      "nid" : 30224,
      "category" : "physical, kitchen cards, physical process, cooking, technique, cooking technique",
      "updated_date" : "Saturday, April 14, 2012 - 9:48",
      "datasource" : "@chachasikes: listing from memory & from scanning lists of food words.",
      "food_color_background" : "C0BFC4",
      "food_color_text" : "131313"
    },
    {
      "name" : "Hot",
      "nid" : 30225,
      "category" : "physical, kitchen cards, physical process, cooking, technique, cooking technique",
      "updated_date" : "Saturday, April 14, 2012 - 9:48",
      "datasource" : "@chachasikes: listing from memory & from scanning lists of food words.",
      "food_color_background" : "C0BFC4",
      "food_color_text" : "131313"
    },
    {
      "name" : "Ice-cold",
      "nid" : 30226,
      "category" : "physical, kitchen cards, physical process, cooking, technique, cooking technique",
      "updated_date" : "Saturday, April 14, 2012 - 9:48",
      "datasource" : "@chachasikes: listing from memory & from scanning lists of food words.",
      "food_color_background" : "C0BFC4",
      "food_color_text" : "131313"
    },
    {
      "name" : "Icy",
      "nid" : 30227,
      "category" : "physical, kitchen cards, physical process, cooking, technique, cooking technique",
      "updated_date" : "Saturday, April 14, 2012 - 9:48",
      "datasource" : "@chachasikes: listing from memory & from scanning lists of food words.",
      "food_color_background" : "C0BFC4",
      "food_color_text" : "131313"
    },
    {
      "name" : "Infuse",
      "nid" : 30228,
      "category" : "physical, kitchen cards, physical process, cooking, technique, cooking technique",
      "updated_date" : "Saturday, April 14, 2012 - 9:48",
      "datasource" : "@chachasikes: listing from memory & from scanning lists of food words.",
      "food_color_background" : "C0BFC4",
      "food_color_text" : "131313"
    },
    {
      "name" : "Inject",
      "nid" : 30229,
      "category" : "physical, kitchen cards, physical process, cooking, technique, cooking technique",
      "updated_date" : "Saturday, April 14, 2012 - 9:48",
      "datasource" : "@chachasikes: listing from memory & from scanning lists of food words.",
      "food_color_background" : "C0BFC4",
      "food_color_text" : "131313"
    },
    {
      "name" : "Juice",
      "nid" : 30230,
      "category" : "physical, kitchen cards, physical process, cooking, technique, cooking technique",
      "updated_date" : "Saturday, April 14, 2012 - 9:48",
      "datasource" : "@chachasikes: listing from memory & from scanning lists of food words.",
      "food_color_background" : "C0BFC4",
      "food_color_text" : "131313"
    },
    {
      "name" : "Lightly-bread",
      "nid" : 30231,
      "category" : "physical, kitchen cards, physical process, cooking, technique, cooking technique",
      "updated_date" : "Saturday, April 14, 2012 - 9:48",
      "datasource" : "@chachasikes: listing from memory & from scanning lists of food words.",
      "food_color_background" : "C0BFC4",
      "food_color_text" : "131313"
    },
    {
      "name" : "Liquefy",
      "nid" : 30232,
      "category" : "physical, kitchen cards, physical process, cooking, technique, cooking technique",
      "updated_date" : "Saturday, April 14, 2012 - 9:48",
      "datasource" : "@chachasikes: listing from memory & from scanning lists of food words.",
      "food_color_background" : "C0BFC4",
      "food_color_text" : "131313"
    },
    {
      "name" : "Macerate",
      "nid" : 30233,
      "category" : "physical, kitchen cards, physical process, cooking, technique, cooking technique",
      "updated_date" : "Saturday, April 14, 2012 - 9:48",
      "datasource" : "@chachasikes: listing from memory & from scanning lists of food words.",
      "food_color_background" : "C0BFC4",
      "food_color_text" : "131313"
    },
    {
      "name" : "Mash",
      "nid" : 30234,
      "category" : "physical, kitchen cards, physical process, cooking, technique, cooking technique",
      "updated_date" : "Saturday, April 14, 2012 - 9:48",
      "datasource" : "@chachasikes: listing from memory & from scanning lists of food words.",
      "food_color_background" : "C0BFC4",
      "food_color_text" : "131313"
    },
    {
      "name" : "Melt",
      "nid" : 30235,
      "category" : "physical, kitchen cards, physical process, cooking, technique, cooking technique",
      "updated_date" : "Saturday, April 14, 2012 - 9:48",
      "datasource" : "@chachasikes: listing from memory & from scanning lists of food words.",
      "food_color_background" : "C0BFC4",
      "food_color_text" : "131313"
    },
    {
      "name" : "Milkify",
      "nid" : 30236,
      "category" : "physical, kitchen cards, physical process, cooking, technique, cooking technique",
      "updated_date" : "Saturday, April 14, 2012 - 9:48",
      "datasource" : "@chachasikes: listing from memory & from scanning lists of food words.",
      "food_color_background" : "C0BFC4",
      "food_color_text" : "131313"
    },
    {
      "name" : "Mince",
      "nid" : 30237,
      "category" : "physical, kitchen cards, physical process, cooking, technique, cooking technique",
      "updated_date" : "Saturday, April 14, 2012 - 9:48",
      "datasource" : "@chachasikes: listing from memory & from scanning lists of food words.",
      "food_color_background" : "C0BFC4",
      "food_color_text" : "131313"
    },
    {
      "name" : "Poach",
      "nid" : 30238,
      "category" : "physical, kitchen cards, physical process, cooking, technique, cooking technique",
      "updated_date" : "Saturday, April 14, 2012 - 9:48",
      "datasource" : "@chachasikes: listing from memory & from scanning lists of food words.",
      "food_color_background" : "C0BFC4",
      "food_color_text" : "131313"
    },
    {
      "name" : "Pound",
      "nid" : 30239,
      "category" : "physical, kitchen cards, physical process, cooking, technique, cooking technique",
      "updated_date" : "Saturday, April 14, 2012 - 9:48",
      "datasource" : "@chachasikes: listing from memory & from scanning lists of food words.",
      "food_color_background" : "C0BFC4",
      "food_color_text" : "131313"
    },
    {
      "name" : "Powder",
      "nid" : 30240,
      "category" : "physical, kitchen cards, physical process, cooking, technique, cooking technique",
      "updated_date" : "Saturday, April 14, 2012 - 9:48",
      "datasource" : "@chachasikes: listing from memory & from scanning lists of food words.",
      "food_color_background" : "C0BFC4",
      "food_color_text" : "131313"
    },
    {
      "name" : "Purée",
      "nid" : 30241,
      "category" : "physical, kitchen cards, physical process, cooking, technique, cooking technique",
      "updated_date" : "Saturday, April 14, 2012 - 9:48",
      "datasource" : "@chachasikes: listing from memory & from scanning lists of food words.",
      "food_color_background" : "C0BFC4",
      "food_color_text" : "131313"
    },
    {
      "name" : "Reduce",
      "nid" : 30242,
      "category" : "physical, kitchen cards, physical process, cooking, technique, cooking technique",
      "updated_date" : "Saturday, April 14, 2012 - 9:48",
      "datasource" : "@chachasikes: listing from memory & from scanning lists of food words.",
      "food_color_background" : "C0BFC4",
      "food_color_text" : "131313"
    },
    {
      "name" : "Rub",
      "nid" : 30243,
      "category" : "physical, kitchen cards, physical process, cooking, technique, cooking technique",
      "updated_date" : "Saturday, April 14, 2012 - 9:48",
      "datasource" : "@chachasikes: listing from memory & from scanning lists of food words.",
      "food_color_background" : "C0BFC4",
      "food_color_text" : "131313"
    },
    {
      "name" : "Shake",
      "nid" : 30245,
      "category" : "physical, kitchen cards, physical process, cooking, technique, cooking technique",
      "updated_date" : "Saturday, April 14, 2012 - 9:48",
      "datasource" : "@chachasikes: listing from memory & from scanning lists of food words.",
      "food_color_background" : "C0BFC4",
      "food_color_text" : "131313"
    },
    {
      "name" : "Shave Ice",
      "nid" : 30246,
      "category" : "physical, kitchen cards, physical process, cooking, technique, cooking technique",
      "updated_date" : "Saturday, April 14, 2012 - 9:48",
      "datasource" : "@chachasikes: listing from memory & from scanning lists of food words.",
      "food_color_background" : "C0BFC4",
      "food_color_text" : "131313"
    },
    {
      "name" : "Shred",
      "nid" : 30247,
      "category" : "physical, kitchen cards, physical process, cooking, technique, cooking technique",
      "updated_date" : "Saturday, April 14, 2012 - 9:48",
      "datasource" : "@chachasikes: listing from memory & from scanning lists of food words.",
      "food_color_background" : "C0BFC4",
      "food_color_text" : "131313"
    },
    {
      "name" : "Slow Roast",
      "nid" : 30248,
      "category" : "physical, kitchen cards, physical process, cooking, technique, cooking technique",
      "updated_date" : "Saturday, April 14, 2012 - 9:48",
      "datasource" : "@chachasikes: listing from memory & from scanning lists of food words.",
      "food_color_background" : "C0BFC4",
      "food_color_text" : "131313"
    },
    {
      "name" : "Soak",
      "nid" : 30249,
      "category" : "physical, kitchen cards, physical process, cooking, technique, cooking technique",
      "updated_date" : "Saturday, April 14, 2012 - 9:48",
      "datasource" : "@chachasikes: listing from memory & from scanning lists of food words.",
      "food_color_background" : "C0BFC4",
      "food_color_text" : "131313"
    },
    {
      "name" : "Steam",
      "nid" : 30250,
      "category" : "physical, kitchen cards, physical process, cooking, technique, cooking technique",
      "updated_date" : "Saturday, April 14, 2012 - 9:48",
      "datasource" : "@chachasikes: listing from memory & from scanning lists of food words.",
      "food_color_background" : "C0BFC4",
      "food_color_text" : "131313"
    },
    {
      "name" : "Steep",
      "nid" : 30251,
      "category" : "physical, kitchen cards, physical process, cooking, technique, cooking technique",
      "updated_date" : "Saturday, April 14, 2012 - 9:48",
      "datasource" : "@chachasikes: listing from memory & from scanning lists of food words.",
      "food_color_background" : "C0BFC4",
      "food_color_text" : "131313"
    },
    {
      "name" : "Stew",
      "nid" : 30252,
      "category" : "physical, kitchen cards, physical process, cooking, technique, cooking technique",
      "updated_date" : "Saturday, April 14, 2012 - 9:48",
      "datasource" : "@chachasikes: listing from memory & from scanning lists of food words.",
      "food_color_background" : "C0BFC4",
      "food_color_text" : "131313"
    },
    {
      "name" : "Sweat",
      "nid" : 30253,
      "category" : "physical, kitchen cards, physical process, cooking, technique, cooking technique",
      "updated_date" : "Saturday, April 14, 2012 - 9:48",
      "datasource" : "@chachasikes: listing from memory & from scanning lists of food words.",
      "food_color_background" : "C0BFC4",
      "food_color_text" : "131313"
    },
    {
      "name" : "Toast",
      "nid" : 30254,
      "category" : "physical, kitchen cards, physical process, cooking, technique, cooking technique",
      "updated_date" : "Saturday, April 14, 2012 - 9:48",
      "datasource" : "@chachasikes: listing from memory & from scanning lists of food words.",
      "food_color_background" : "C0BFC4",
      "food_color_text" : "131313"
    },
    {
      "name" : "Toss",
      "nid" : 30255,
      "category" : "physical, kitchen cards, physical process, cooking, technique, cooking technique",
      "updated_date" : "Saturday, April 14, 2012 - 9:48",
      "datasource" : "@chachasikes: listing from memory & from scanning lists of food words.",
      "food_color_background" : "C0BFC4",
      "food_color_text" : "131313"
    },
    {
      "name" : "Vacuum Pack",
      "nid" : 30257,
      "category" : "physical, kitchen cards, physical process, cooking, technique, cooking technique",
      "updated_date" : "Saturday, April 14, 2012 - 9:48",
      "datasource" : "@chachasikes: listing from memory & from scanning lists of food words.",
      "food_color_background" : "C0BFC4",
      "food_color_text" : "131313"
    },
    {
      "name" : "Whip",
      "nid" : 30256,
      "category" : "physical, kitchen cards, physical process, cooking, technique, cooking technique",
      "updated_date" : "Saturday, April 14, 2012 - 9:48",
      "datasource" : "@chachasikes: listing from memory & from scanning lists of food words.",
      "food_color_background" : "C0BFC4",
      "food_color_text" : "131313"
    },
 {
      "name" : "Single Dish",
      "nid" : 30000,
      "datasource" : "@chachasikes: listing from memory & from scanning lists of food words.",
      "update_date" : "Saturday, April 14, 2012 - 9:38",
      "description" : null,
      "category" : "shape, kitchen cards, process, form, food presentation",
      "food_color_background" : "E0EDFE",
      "food_color_text" : "131313"
    },
    {
      "name" : "Animal",
      "nid" : 30001,
      "datasource" : "@chachasikes: listing from memory & from scanning lists of food words.",
      "update_date" : "Saturday, April 14, 2012 - 9:38",
      "description" : null,
      "category" : "shape, kitchen cards, process, form, food presentation",
      "food_color_background" : "E0EDFE",
      "food_color_text" : "131313"
    },
    {
      "name" : "Assortment",
      "nid" : 30002,
      "datasource" : "@chachasikes: listing from memory & from scanning lists of food words.",
      "update_date" : "Saturday, April 14, 2012 - 9:38",
      "description" : null,
      "category" : "shape, kitchen cards, process, form, food presentation",
      "food_color_background" : "E0EDFE",
      "food_color_text" : "131313"
    },
    {
      "name" : "Cake",
      "nid" : 30003,
      "datasource" : "@chachasikes: listing from memory & from scanning lists of food words.",
      "update_date" : "Saturday, April 14, 2012 - 9:38",
      "description" : null,
      "category" : "shape, kitchen cards, process, form, food presentation",
      "food_color_background" : "E0EDFE",
      "food_color_text" : "131313"
    },
    {
      "name" : "Casserole",
      "nid" : 30004,
      "datasource" : "@chachasikes: listing from memory & from scanning lists of food words.",
      "update_date" : "Saturday, April 14, 2012 - 9:38",
      "description" : null,
      "category" : "shape, kitchen cards, process, form, food presentation",
      "food_color_background" : "E0EDFE",
      "food_color_text" : "131313"
    },
    {
      "name" : "Chunk",
      "nid" : 30005,
      "datasource" : "@chachasikes: listing from memory & from scanning lists of food words.",
      "update_date" : "Saturday, April 14, 2012 - 9:38",
      "description" : null,
      "category" : "shape, kitchen cards, process, form, food presentation",
      "food_color_background" : "E0EDFE",
      "food_color_text" : "131313"
    },
    {
      "name" : "Circle",
      "nid" : 30006,
      "datasource" : "@chachasikes: listing from memory & from scanning lists of food words.",
      "update_date" : "Saturday, April 14, 2012 - 9:38",
      "description" : null,
      "category" : "shape, kitchen cards, process, form, food presentation",
      "food_color_background" : "E0EDFE",
      "food_color_text" : "131313"
    },
    {
      "name" : "Cookie Cut",
      "nid" : 30007,
      "datasource" : "@chachasikes: listing from memory & from scanning lists of food words.",
      "update_date" : "Saturday, April 14, 2012 - 9:38",
      "description" : null,
      "category" : "shape, kitchen cards, process, form, food presentation",
      "food_color_background" : "E0EDFE",
      "food_color_text" : "131313"
    },
    {
      "name" : "Dab",
      "nid" : 30008,
      "datasource" : "@chachasikes: listing from memory & from scanning lists of food words.",
      "update_date" : "Saturday, April 14, 2012 - 9:38",
      "description" : null,
      "category" : "shape, kitchen cards, process, form, food presentation",
      "food_color_background" : "E0EDFE",
      "food_color_text" : "131313"
    },
    {
      "name" : "Dip",
      "nid" : 30009,
      "datasource" : "@chachasikes: listing from memory & from scanning lists of food words.",
      "update_date" : "Saturday, April 14, 2012 - 9:38",
      "description" : null,
      "category" : "shape, kitchen cards, process, form, food presentation",
      "food_color_background" : "E0EDFE",
      "food_color_text" : "131313"
    },
    {
      "name" : "Dollop",
      "nid" : 30010,
      "datasource" : "@chachasikes: listing from memory & from scanning lists of food words.",
      "update_date" : "Saturday, April 14, 2012 - 9:38",
      "description" : null,
      "category" : "shape, kitchen cards, process, form, food presentation",
      "food_color_background" : "E0EDFE",
      "food_color_text" : "131313"
    },
    {
      "name" : "Dumpling",
      "nid" : 30011,
      "datasource" : "@chachasikes: listing from memory & from scanning lists of food words.",
      "update_date" : "Saturday, April 14, 2012 - 9:38",
      "description" : null,
      "category" : "shape, kitchen cards, process, form, food presentation",
      "food_color_background" : "E0EDFE",
      "food_color_text" : "131313"
    },
    {
      "name" : "Extrude",
      "nid" : 30012,
      "datasource" : "@chachasikes: listing from memory & from scanning lists of food words.",
      "update_date" : "Saturday, April 14, 2012 - 9:38",
      "description" : null,
      "category" : "shape, kitchen cards, process, form, food presentation",
      "food_color_background" : "E0EDFE",
      "food_color_text" : "131313"
    },
    {
      "name" : "Filament",
      "nid" : 30013,
      "datasource" : "@chachasikes: listing from memory & from scanning lists of food words.",
      "update_date" : "Saturday, April 14, 2012 - 9:38",
      "description" : null,
      "category" : "shape, kitchen cards, process, form, food presentation",
      "food_color_background" : "E0EDFE",
      "food_color_text" : "131313"
    },
    {
      "name" : "Fillet",
      "nid" : 30014,
      "datasource" : "@chachasikes: listing from memory & from scanning lists of food words.",
      "update_date" : "Saturday, April 14, 2012 - 9:38",
      "description" : null,
      "category" : "shape, kitchen cards, process, form, food presentation",
      "food_color_background" : "E0EDFE",
      "food_color_text" : "131313"
    },
    {
      "name" : "Finger-food",
      "nid" : 30015,
      "datasource" : "@chachasikes: listing from memory & from scanning lists of food words.",
      "update_date" : "Saturday, April 14, 2012 - 9:38",
      "description" : null,
      "category" : "shape, kitchen cards, process, form, food presentation",
      "food_color_background" : "E0EDFE",
      "food_color_text" : "131313"
    },
    {
      "name" : "Flower",
      "nid" : 30016,
      "datasource" : "@chachasikes: listing from memory & from scanning lists of food words.",
      "update_date" : "Saturday, April 14, 2012 - 9:38",
      "description" : null,
      "category" : "shape, kitchen cards, process, form, food presentation",
      "food_color_background" : "E0EDFE",
      "food_color_text" : "131313"
    },
    {
      "name" : "Generous",
      "nid" : 30017,
      "datasource" : "@chachasikes: listing from memory & from scanning lists of food words.",
      "update_date" : "Saturday, April 14, 2012 - 9:38",
      "description" : null,
      "category" : "shape, kitchen cards, process, form, food presentation",
      "food_color_background" : "E0EDFE",
      "food_color_text" : "131313"
    },
    {
      "name" : "Grated",
      "nid" : 30018,
      "datasource" : "@chachasikes: listing from memory & from scanning lists of food words.",
      "update_date" : "Saturday, April 14, 2012 - 9:38",
      "description" : null,
      "category" : "shape, kitchen cards, process, form, food presentation",
      "food_color_background" : "E0EDFE",
      "food_color_text" : "131313"
    },
    {
      "name" : "Heart",
      "nid" : 30019,
      "datasource" : "@chachasikes: listing from memory & from scanning lists of food words.",
      "update_date" : "Saturday, April 14, 2012 - 9:38",
      "description" : null,
      "category" : "shape, kitchen cards, process, form, food presentation",
      "food_color_background" : "E0EDFE",
      "food_color_text" : "131313"
    },
    {
      "name" : "Jellyroll",
      "nid" : 30020,
      "datasource" : "@chachasikes: listing from memory & from scanning lists of food words.",
      "update_date" : "Saturday, April 14, 2012 - 9:38",
      "description" : null,
      "category" : "shape, kitchen cards, process, form, food presentation",
      "food_color_background" : "E0EDFE",
      "food_color_text" : "131313"
    },
    {
      "name" : "Julienne",
      "nid" : 30021,
      "datasource" : "@chachasikes: listing from memory & from scanning lists of food words.",
      "update_date" : "Saturday, April 14, 2012 - 9:38",
      "description" : null,
      "category" : "shape, kitchen cards, process, form, food presentation",
      "food_color_background" : "E0EDFE",
      "food_color_text" : "131313"
    },
    {
      "name" : "Layer",
      "nid" : 30022,
      "datasource" : "@chachasikes: listing from memory & from scanning lists of food words.",
      "update_date" : "Saturday, April 14, 2012 - 9:38",
      "description" : null,
      "category" : "shape, kitchen cards, process, form, food presentation",
      "food_color_background" : "E0EDFE",
      "food_color_text" : "131313"
    },
    {
      "name" : "Leaf",
      "nid" : 30023,
      "datasource" : "@chachasikes: listing from memory & from scanning lists of food words.",
      "update_date" : "Saturday, April 14, 2012 - 9:38",
      "description" : null,
      "category" : "shape, kitchen cards, process, form, food presentation",
      "food_color_background" : "E0EDFE",
      "food_color_text" : "131313"
    },
    {
      "name" : "Loaf",
      "nid" : 30024,
      "datasource" : "@chachasikes: listing from memory & from scanning lists of food words.",
      "update_date" : "Saturday, April 14, 2012 - 9:38",
      "description" : null,
      "category" : "shape, kitchen cards, process, form, food presentation",
      "food_color_background" : "E0EDFE",
      "food_color_text" : "131313"
    },
    {
      "name" : "Lump",
      "nid" : 30025,
      "datasource" : "@chachasikes: listing from memory & from scanning lists of food words.",
      "update_date" : "Saturday, April 14, 2012 - 9:38",
      "description" : null,
      "category" : "shape, kitchen cards, process, form, food presentation",
      "food_color_background" : "E0EDFE",
      "food_color_text" : "131313"
    },
    {
      "name" : "Mash",
      "nid" : 30026,
      "datasource" : "@chachasikes: listing from memory & from scanning lists of food words.",
      "update_date" : "Saturday, April 14, 2012 - 9:38",
      "description" : null,
      "category" : "shape, kitchen cards, process, form, food presentation",
      "food_color_background" : "E0EDFE",
      "food_color_text" : "131313"
    },
    {
      "name" : "Mince",
      "nid" : 30027,
      "datasource" : "@chachasikes: listing from memory & from scanning lists of food words.",
      "update_date" : "Saturday, April 14, 2012 - 9:38",
      "description" : null,
      "category" : "shape, kitchen cards, process, form, food presentation",
      "food_color_background" : "E0EDFE",
      "food_color_text" : "131313"
    },
    {
      "name" : "Mixed",
      "nid" : 30028,
      "datasource" : "@chachasikes: listing from memory & from scanning lists of food words.",
      "update_date" : "Saturday, April 14, 2012 - 9:38",
      "description" : null,
      "category" : "shape, kitchen cards, process, form, food presentation",
      "food_color_background" : "E0EDFE",
      "food_color_text" : "131313"
    },
    {
      "name" : "Mold",
      "nid" : 30029,
      "datasource" : "@chachasikes: listing from memory & from scanning lists of food words.",
      "update_date" : "Saturday, April 14, 2012 - 9:38",
      "description" : null,
      "category" : "shape, kitchen cards, process, form, food presentation",
      "food_color_background" : "E0EDFE",
      "food_color_text" : "131313"
    },
    {
      "name" : "Nibble",
      "nid" : 30030,
      "datasource" : "@chachasikes: listing from memory & from scanning lists of food words.",
      "update_date" : "Saturday, April 14, 2012 - 9:38",
      "description" : null,
      "category" : "shape, kitchen cards, process, form, food presentation",
      "food_color_background" : "E0EDFE",
      "food_color_text" : "131313"
    },
    {
      "name" : "Noodle",
      "nid" : 30031,
      "datasource" : "@chachasikes: listing from memory & from scanning lists of food words.",
      "update_date" : "Saturday, April 14, 2012 - 9:38",
      "description" : null,
      "category" : "shape, kitchen cards, process, form, food presentation",
      "food_color_background" : "E0EDFE",
      "food_color_text" : "131313"
    },
    {
      "name" : "Pancake",
      "nid" : 30032,
      "datasource" : "@chachasikes: listing from memory & from scanning lists of food words.",
      "update_date" : "Saturday, April 14, 2012 - 9:38",
      "description" : null,
      "category" : "shape, kitchen cards, process, form, food presentation",
      "food_color_background" : "E0EDFE",
      "food_color_text" : "131313"
    },
    {
      "name" : "Pastry",
      "nid" : 30033,
      "datasource" : "@chachasikes: listing from memory & from scanning lists of food words.",
      "update_date" : "Saturday, April 14, 2012 - 9:38",
      "description" : null,
      "category" : "shape, kitchen cards, process, form, food presentation",
      "food_color_background" : "E0EDFE",
      "food_color_text" : "131313"
    },
    {
      "name" : "Pastry Wrapped",
      "nid" : 30034,
      "datasource" : "@chachasikes: listing from memory & from scanning lists of food words.",
      "update_date" : "Saturday, April 14, 2012 - 9:38",
      "description" : null,
      "category" : "shape, kitchen cards, process, form, food presentation",
      "food_color_background" : "E0EDFE",
      "food_color_text" : "131313"
    },
    {
      "name" : "Pate",
      "nid" : 30035,
      "datasource" : "@chachasikes: listing from memory & from scanning lists of food words.",
      "update_date" : "Saturday, April 14, 2012 - 9:38",
      "description" : null,
      "category" : "shape, kitchen cards, process, form, food presentation",
      "food_color_background" : "E0EDFE",
      "food_color_text" : "131313"
    },
    {
      "name" : "Pinch",
      "nid" : 30036,
      "datasource" : "@chachasikes: listing from memory & from scanning lists of food words.",
      "update_date" : "Saturday, April 14, 2012 - 9:38",
      "description" : null,
      "category" : "shape, kitchen cards, process, form, food presentation",
      "food_color_background" : "E0EDFE",
      "food_color_text" : "131313"
    },
    {
      "name" : "Pouch",
      "nid" : 30037,
      "datasource" : "@chachasikes: listing from memory & from scanning lists of food words.",
      "update_date" : "Saturday, April 14, 2012 - 9:38",
      "description" : null,
      "category" : "shape, kitchen cards, process, form, food presentation",
      "food_color_background" : "E0EDFE",
      "food_color_text" : "131313"
    },
    {
      "name" : "Prep",
      "nid" : 30038,
      "datasource" : "@chachasikes: listing from memory & from scanning lists of food words.",
      "update_date" : "Saturday, April 14, 2012 - 9:38",
      "description" : null,
      "category" : "shape, kitchen cards, process, form, food presentation",
      "food_color_background" : "E0EDFE",
      "food_color_text" : "131313"
    },
    {
      "name" : "Ravoli",
      "nid" : 30039,
      "datasource" : "@chachasikes: listing from memory & from scanning lists of food words.",
      "update_date" : "Saturday, April 14, 2012 - 9:38",
      "description" : null,
      "category" : "shape, kitchen cards, process, form, food presentation",
      "food_color_background" : "E0EDFE",
      "food_color_text" : "131313"
    },
    {
      "name" : "Roll",
      "nid" : 30040,
      "datasource" : "@chachasikes: listing from memory & from scanning lists of food words.",
      "update_date" : "Saturday, April 14, 2012 - 9:38",
      "description" : null,
      "category" : "shape, kitchen cards, process, form, food presentation",
      "food_color_background" : "E0EDFE",
      "food_color_text" : "131313"
    },
    {
      "name" : "Salad",
      "nid" : 30041,
      "datasource" : "@chachasikes: listing from memory & from scanning lists of food words.",
      "update_date" : "Saturday, April 14, 2012 - 9:38",
      "description" : null,
      "category" : "shape, kitchen cards, process, form, food presentation",
      "food_color_background" : "E0EDFE",
      "food_color_text" : "131313"
    },
    {
      "name" : "Sandwich",
      "nid" : 30042,
      "datasource" : "@chachasikes: listing from memory & from scanning lists of food words.",
      "update_date" : "Saturday, April 14, 2012 - 9:38",
      "description" : null,
      "category" : "shape, kitchen cards, process, form, food presentation",
      "food_color_background" : "E0EDFE",
      "food_color_text" : "131313"
    },
    {
      "name" : "Sculpt",
      "nid" : 30043,
      "datasource" : "@chachasikes: listing from memory & from scanning lists of food words.",
      "update_date" : "Saturday, April 14, 2012 - 9:38",
      "description" : null,
      "category" : "shape, kitchen cards, process, form, food presentation",
      "food_color_background" : "E0EDFE",
      "food_color_text" : "131313"
    },
    {
      "name" : "Shred",
      "nid" : 30044,
      "datasource" : "@chachasikes: listing from memory & from scanning lists of food words.",
      "update_date" : "Saturday, April 14, 2012 - 9:38",
      "description" : null,
      "category" : "shape, kitchen cards, process, form, food presentation",
      "food_color_background" : "E0EDFE",
      "food_color_text" : "131313"
    },
    {
      "name" : "Small",
      "nid" : 30045,
      "datasource" : "@chachasikes: listing from memory & from scanning lists of food words.",
      "update_date" : "Saturday, April 14, 2012 - 9:38",
      "description" : null,
      "category" : "shape, kitchen cards, process, form, food presentation",
      "food_color_background" : "E0EDFE",
      "food_color_text" : "131313"
    },
    {
      "name" : "Smash",
      "nid" : 30046,
      "datasource" : "@chachasikes: listing from memory & from scanning lists of food words.",
      "update_date" : "Saturday, April 14, 2012 - 9:38",
      "description" : null,
      "category" : "shape, kitchen cards, process, form, food presentation",
      "food_color_background" : "E0EDFE",
      "food_color_text" : "131313"
    },
    {
      "name" : "Smooth",
      "nid" : 30047,
      "datasource" : "@chachasikes: listing from memory & from scanning lists of food words.",
      "update_date" : "Saturday, April 14, 2012 - 9:38",
      "description" : null,
      "category" : "shape, kitchen cards, process, form, food presentation",
      "food_color_background" : "E0EDFE",
      "food_color_text" : "131313"
    },
    {
      "name" : "Smother",
      "nid" : 30048,
      "datasource" : "@chachasikes: listing from memory & from scanning lists of food words.",
      "update_date" : "Saturday, April 14, 2012 - 9:38",
      "description" : null,
      "category" : "shape, kitchen cards, process, form, food presentation",
      "food_color_background" : "E0EDFE",
      "food_color_text" : "131313"
    },
    {
      "name" : "Soft",
      "nid" : 30049,
      "datasource" : "@chachasikes: listing from memory & from scanning lists of food words.",
      "update_date" : "Saturday, April 14, 2012 - 9:38",
      "description" : null,
      "category" : "shape, kitchen cards, process, form, food presentation",
      "food_color_background" : "E0EDFE",
      "food_color_text" : "131313"
    },
    {
      "name" : "Soup",
      "nid" : 30050,
      "datasource" : "@chachasikes: listing from memory & from scanning lists of food words.",
      "update_date" : "Saturday, April 14, 2012 - 9:38",
      "description" : null,
      "category" : "shape, kitchen cards, process, form, food presentation",
      "food_color_background" : "E0EDFE",
      "food_color_text" : "131313"
    },
    {
      "name" : "Spiral-cut",
      "nid" : 30051,
      "datasource" : "@chachasikes: listing from memory & from scanning lists of food words.",
      "update_date" : "Saturday, April 14, 2012 - 9:38",
      "description" : null,
      "category" : "shape, kitchen cards, process, form, food presentation",
      "food_color_background" : "E0EDFE",
      "food_color_text" : "131313"
    },
    {
      "name" : "Sprinkle",
      "nid" : 30052,
      "datasource" : "@chachasikes: listing from memory & from scanning lists of food words.",
      "update_date" : "Saturday, April 14, 2012 - 9:38",
      "description" : null,
      "category" : "shape, kitchen cards, process, form, food presentation",
      "food_color_background" : "E0EDFE",
      "food_color_text" : "131313"
    },
    {
      "name" : "Square",
      "nid" : 30053,
      "datasource" : "@chachasikes: listing from memory & from scanning lists of food words.",
      "update_date" : "Saturday, April 14, 2012 - 9:38",
      "description" : null,
      "category" : "shape, kitchen cards, process, form, food presentation",
      "food_color_background" : "E0EDFE",
      "food_color_text" : "131313"
    },
    {
      "name" : "Star",
      "nid" : 30054,
      "datasource" : "@chachasikes: listing from memory & from scanning lists of food words.",
      "update_date" : "Saturday, April 14, 2012 - 9:38",
      "description" : null,
      "category" : "shape, kitchen cards, process, form, food presentation",
      "food_color_background" : "E0EDFE",
      "food_color_text" : "131313"
    },
    {
      "name" : "Strip",
      "nid" : 30055,
      "datasource" : "@chachasikes: listing from memory & from scanning lists of food words.",
      "update_date" : "Saturday, April 14, 2012 - 9:38",
      "description" : null,
      "category" : "shape, kitchen cards, process, form, food presentation",
      "food_color_background" : "E0EDFE",
      "food_color_text" : "131313"
    },
    {
      "name" : "Stuff",
      "nid" : 30056,
      "datasource" : "@chachasikes: listing from memory & from scanning lists of food words.",
      "update_date" : "Saturday, April 14, 2012 - 9:38",
      "description" : null,
      "category" : "shape, kitchen cards, process, form, food presentation",
      "food_color_background" : "E0EDFE",
      "food_color_text" : "131313"
    },
    {
      "name" : "Surprise",
      "nid" : 30057,
      "datasource" : "@chachasikes: listing from memory & from scanning lists of food words.",
      "update_date" : "Saturday, April 14, 2012 - 9:38",
      "description" : null,
      "category" : "shape, kitchen cards, process, form, food presentation",
      "food_color_background" : "E0EDFE",
      "food_color_text" : "131313"
    },
    {
      "name" : "Tagliatelle",
      "nid" : 30058,
      "datasource" : "@chachasikes: listing from memory & from scanning lists of food words.",
      "update_date" : "Saturday, April 14, 2012 - 9:38",
      "description" : null,
      "category" : "shape, kitchen cards, process, form, food presentation",
      "food_color_background" : "E0EDFE",
      "food_color_text" : "131313"
    },
    {
      "name" : "Thick",
      "nid" : 30059,
      "datasource" : "@chachasikes: listing from memory & from scanning lists of food words.",
      "update_date" : "Saturday, April 14, 2012 - 9:38",
      "description" : null,
      "category" : "shape, kitchen cards, process, form, food presentation",
      "food_color_background" : "E0EDFE",
      "food_color_text" : "131313"
    },
    {
      "name" : "Thin",
      "nid" : 30060,
      "datasource" : "@chachasikes: listing from memory & from scanning lists of food words.",
      "update_date" : "Saturday, April 14, 2012 - 9:38",
      "description" : null,
      "category" : "shape, kitchen cards, process, form, food presentation",
      "food_color_background" : "E0EDFE",
      "food_color_text" : "131313"
    },
    {
      "name" : "Top",
      "nid" : 30061,
      "datasource" : "@chachasikes: listing from memory & from scanning lists of food words.",
      "update_date" : "Saturday, April 14, 2012 - 9:38",
      "description" : null,
      "category" : "shape, kitchen cards, process, form, food presentation",
      "food_color_background" : "E0EDFE",
      "food_color_text" : "131313"
    },
    {
      "name" : "Toss",
      "nid" : 30062,
      "datasource" : "@chachasikes: listing from memory & from scanning lists of food words.",
      "update_date" : "Saturday, April 14, 2012 - 9:38",
      "description" : null,
      "category" : "shape, kitchen cards, process, form, food presentation",
      "food_color_background" : "E0EDFE",
      "food_color_text" : "131313"
    },
    {
      "name" : "Triangle",
      "nid" : 30063,
      "datasource" : "@chachasikes: listing from memory & from scanning lists of food words.",
      "update_date" : "Saturday, April 14, 2012 - 9:38",
      "description" : null,
      "category" : "shape, kitchen cards, process, form, food presentation",
      "food_color_background" : "E0EDFE",
      "food_color_text" : "131313"
    },
    {
      "name" : "Wrap",
      "nid" : 30064,
      "datasource" : "@chachasikes: listing from memory & from scanning lists of food words.",
      "update_date" : "Saturday, April 14, 2012 - 9:38",
      "description" : null,
      "category" : "shape, kitchen cards, process, form, food presentation",
      "food_color_background" : "E0EDFE",
      "food_color_text" : "131313"
    },
    {
      "name" : "Liquid in Center",
      "nid" : 30065,
      "datasource" : "@chachasikes: listing from memory & from scanning lists of food words.",
      "update_date" : "Saturday, April 14, 2012 - 9:38",
      "description" : null,
      "category" : "shape, kitchen cards, process, form, food presentation",
      "food_color_background" : "E0EDFE",
      "food_color_text" : "131313"
    },
    {
      "name" : "Gel Center",
      "nid" : 30066,
      "datasource" : "@chachasikes: listing from memory & from scanning lists of food words.",
      "update_date" : "Saturday, April 14, 2012 - 9:38",
      "description" : null,
      "category" : "shape, kitchen cards, process, form, food presentation",
      "food_color_background" : "E0EDFE",
      "food_color_text" : "131313"
    },
    {
      "name" : "Semi-solid Center",
      "nid" : 30067,
      "datasource" : "@chachasikes: listing from memory & from scanning lists of food words.",
      "update_date" : "Saturday, April 14, 2012 - 9:38",
      "description" : null,
      "category" : "shape, kitchen cards, process, form, food presentation",
      "food_color_background" : "E0EDFE",
      "food_color_text" : "131313"
    },
    {
      "name" : "Solid Center",
      "nid" : 30068,
      "datasource" : "@chachasikes: listing from memory & from scanning lists of food words.",
      "update_date" : "Saturday, April 14, 2012 - 9:38",
      "description" : null,
      "category" : "shape, kitchen cards, process, form, food presentation",
      "food_color_background" : "E0EDFE",
      "food_color_text" : "131313"
    },
    {
      "name" : "Air in Center",
      "nid" : 30069,
      "datasource" : "@chachasikes: listing from memory & from scanning lists of food words.",
      "update_date" : "Saturday, April 14, 2012 - 9:38",
      "description" : null,
      "category" : "shape, kitchen cards, process, form, food presentation",
      "food_color_background" : "E0EDFE",
      "food_color_text" : "131313"
    }
  ]
}